README.md
setup.cfg
setup.py
distributions_oop_tut/Binomialdistribution.py
distributions_oop_tut/Gaussiandistribution.py
distributions_oop_tut/Generaldistribution.py
distributions_oop_tut/__init__.py
distributions_oop_tut.egg-info/PKG-INFO
distributions_oop_tut.egg-info/SOURCES.txt
distributions_oop_tut.egg-info/dependency_links.txt
distributions_oop_tut.egg-info/not-zip-safe
distributions_oop_tut.egg-info/top_level.txt